[
    {
        "name": "latest",
        "version": "unreleased",
        "url": "https://compas.dev/compas/latest/"
    },
    {
        "name": "v2.0.0-alpha.1",
        "version": "2.0.0-alpha.1",
        "url": "https://compas.dev/compas/2.0.0-alpha.1/"
    },
    {
        "name": "v1.17.7 (stable)",
        "version": "1.17.8",
        "url": "https://compas.dev/compas/1.17.8/"
    },
    {
        "version": "1.16.0",
        "url": "https://compas.dev/compas/1.16.0/"
    },
    {
        "version": "1.15.0",
        "url": "https://compas.dev/compas/1.15.0/"
    }
]
